LICENSE
README.md
pyproject.toml
setup.cfg
setup.py
accupy/__init__.py
accupy/dot.py
accupy/ill_cond.py
accupy/sums.py
accupy.egg-info/PKG-INFO
accupy.egg-info/SOURCES.txt
accupy.egg-info/dependency_links.txt
accupy.egg-info/not-zip-safe
accupy.egg-info/requires.txt
accupy.egg-info/top_level.txt
src/pybind11.cpp