Metadata-Version: 2.1
Name: accupy
Version: 0.3.6
Summary: Accurate sums and dot products for Python
Home-page: https://github.com/nschloe/accupy
Author: Nico Schlömer
Author-email: nico.schloemer@gmail.com
License: GPL-3.0-or-later
Project-URL: Code, https://github.com/nschloe/accupy
Project-URL: Issues, https://github.com/nschloe/accupy/issues
Project-URL: Funding, https://github.com/sponsors/nschloe
Keywords: mathematics,physics,engineering,cgal,mesh,mesh generation
Platform: UNKNOWN
Classifier: Development Status :: 4 - Beta
Classifier: License :: OSI Approved :: GNU General Public License v3 or later (GPLv3+)
Classifier: Operating System :: OS Independent
Classifier: Programming Language :: Python
Classifier: Programming Language :: Python :: 3
Classifier: Programming Language :: Python :: 3.7
Classifier: Programming Language :: Python :: 3.8
Classifier: Programming Language :: Python :: 3.9
Classifier: Topic :: Scientific/Engineering
Classifier: Topic :: Scientific/Engineering :: Mathematics
Requires-Python: >=3.7
License-File: LICENSE
